{"content":[{"id":"31196a14","settings":{"layout":"full_width","height":"min-height","custom_height":{"unit":"px","size":"900","sizes":[]},"structure":"20","custom_height_tablet":{"unit":"px","size":"0","sizes":[]},"background_overlay_background":"classic","background_overlay_image_tablet":{"url":"https:\/\/ultra.inspirylabs.com\/condominium\/wp-content\/uploads\/sites\/8\/2023\/04\/hero-section.jpg","id":"1089","size":"","alt":"","source":"library"},"background_overlay_repeat_tablet":"no-repeat","background_overlay_size_tablet":"cover","background_overlay_opacity_tablet":{"unit":"px","size":"0.1","sizes":[]},"padding_tablet":{"unit":"px","top":"80","right":"0","bottom":"0","left":"0","isLinked":""},"padding_mobile":{"unit":"px","top":"140","right":"0","bottom":"0","left":"0","isLinked":""}},"elements":[{"id":"73e8479e","settings":{"_column_size":"50","_inline_size":"30","_inline_size_tablet":"99","padding_mobile":{"unit":"px","top":"0","right":"10","bottom":"0","left":"10","isLinked":""}},"elements":[{"id":"4ada82f6","settings":{"content_width":{"unit":"px","size":"530","sizes":[]},"text_align":"left","padding":{"unit":"px","top":"40","right":"0","bottom":"0","left":"0","isLinked":""},"content_width_tablet":{"unit":"px","size":"700","sizes":[]},"padding_tablet":{"unit":"px","top":"40","right":"0","bottom":"40","left":"0","isLinked":""}},"elements":[{"id":"3a77a7c8","settings":{"_column_size":"100","content_position":"center","margin":{"unit":"%","top":"0","right":"-30","bottom":"0","left":"30","isLinked":""},"margin_tablet":{"unit":"%","top":"0","right":"0","bottom":"0","left":"0","isLinked":"1"},"margin_mobile":{"unit":"%","top":"","right":"","bottom":"","left":"","isLinked":"1"},"z_index":"9"},"elements":[{"id":"3a904dc4","settings":{"title":"3, 4 &amp; 5 BHK Luxurious Apartment","_margin":{"unit":"px","top":"0","right":"0","bottom":"0","left":"0","isLinked":""},"__globals__":{"typography_typography":""},"title_color":"#0A1510","typography_typography":"custom","typography_font_family":"Archivo","typography_font_size":{"unit":"px","size":"20","sizes":[]},"typography_font_weight":"400","typography_line_height":{"unit":"custom","size":"100%","sizes":[]},"typography_line_height_laptop":{"unit":"custom","size":"","sizes":[]},"typography_line_height_tablet_extra":{"unit":"custom","size":"","sizes":[]},"typography_line_height_tablet":{"unit":"custom","size":"","sizes":[]},"typography_line_height_mobile":{"unit":"custom","size":"","sizes":[]},"typography_word_spacing":{"unit":"em","size":"","sizes":[]}},"elements":[],"isInner":false,"widgetType":"heading","elType":"widget"},{"id":"304e37c2","settings":{"title":"Elegance\nThrough\nSimplicity","typography_typography":"custom","typography_font_family":"Archivo Black","typography_font_size":{"unit":"px","size":"100","sizes":[]},"typography_font_weight":"600","typography_line_height":{"unit":"em","size":"1.2","sizes":[]},"typography_line_height_tablet":{"unit":"rem","size":"","sizes":[]},"typography_line_height_mobile":{"unit":"rem","size":"","sizes":[]},"__globals__":{"typography_typography":""},"_margin":{"unit":"px","top":"-10","right":"0","bottom":"0","left":"-8","isLinked":""},"_padding":{"unit":"px","top":"0","right":"0","bottom":"0","left":"0","isLinked":""},"typography_font_size_tablet":{"unit":"px","size":"70","sizes":[]},"typography_font_size_mobile":{"unit":"px","size":"48","sizes":[]},"title_color":"#0A1510"},"elements":[],"isInner":false,"widgetType":"heading","elType":"widget"},{"id":"be39d4a","settings":{"width":{"unit":"px","size":"100","sizes":[]},"width_tablet":{"unit":"px","size":"","sizes":[]},"width_mobile":{"unit":"px","size":"","sizes":[]},"text":"Divider","color":"#3A7658A3","weight":{"unit":"px","size":"3","sizes":[]},"gap":{"unit":"px","size":"0","sizes":[]},"_margin":{"unit":"px","top":"-15","right":"0","bottom":"0","left":"0","isLinked":""},"__globals__":{"color":""}},"elements":[],"isInner":false,"widgetType":"divider","elType":"widget"},{"id":"3c99974f","settings":{"icon_list":[{"text":"Hi-end Furnitures","selected_icon":{"value":{"url":"https:\/\/ultra.inspirylabs.com\/condominium\/wp-content\/uploads\/sites\/8\/2023\/04\/sofa.svg","id":"380"},"library":"svg"},"_id":"8d2c3da"},{"text":"24 Floors","selected_icon":{"value":{"url":"https:\/\/ultra.inspirylabs.com\/condominium\/wp-content\/uploads\/sites\/8\/2023\/04\/building.svg","id":"379"},"library":"svg"},"_id":"854eaab"},{"text":"Natural Lighting","selected_icon":{"value":{"url":"https:\/\/ultra.inspirylabs.com\/condominium\/wp-content\/uploads\/sites\/8\/2023\/04\/sun.svg","id":"382"},"library":"svg"},"_id":"c9ced18"}],"icon_typography_typography":"custom","icon_typography_font_family":"Archivo","icon_typography_font_size":{"unit":"px","size":"18","sizes":[]},"icon_typography_font_weight":"400","__globals__":{"text_color":"","icon_color":""},"icon_color":"#3A7658","text_color":"#0A1510","space_between":{"unit":"px","size":"12","sizes":[]},"icon_size":{"unit":"px","size":"20","sizes":[]}},"elements":[],"isInner":false,"widgetType":"icon-list","elType":"widget"},{"id":"4c13553e","settings":{"button_text":"Schedule a Tour","button_text_url":{"url":"#rh-schedule","is_external":"","nofollow":"","custom_attributes":""},"button_type":"slide-in-left","button_typography_typography":"custom","button_typography_font_family":"Archivo","button_typography_font_size":{"unit":"px","size":"20","sizes":[]},"button_typography_font_weight":"600","button_typography_line_height":{"unit":"px","size":"35","sizes":[]},"button_text_color":"#FFFFFF","button_text_hover_color":"#FFFFFF","button_background_color":"#3A7658","button_background_hover_color":"#000000","__globals__":{"button_background_color":""},"button_icon":{"value":"","library":""}},"elements":[],"isInner":false,"widgetType":"rhea-button-widget","elType":"widget"}],"isInner":"1","elType":"column"}],"isInner":"1","elType":"section"}],"isInner":"","elType":"column"},{"id":"285ce52c","settings":{"_column_size":"50","_inline_size":"70","background_background":"classic","background_image":{"url":"https:\/\/ultra.inspirylabs.com\/condominium\/wp-content\/uploads\/sites\/8\/2023\/04\/hero-section.jpg","id":"1089","size":"","alt":"","source":"library"},"background_position":"center center","background_repeat":"no-repeat","background_size":"cover","hide_tablet":"hidden-tablet","hide_mobile":"hidden-mobile"},"elements":[{"id":"6f399c6","settings":{"height_inner":"min-height","custom_height_inner":{"unit":"px","size":"900","sizes":[]},"structure":"20","background_background":"classic","background_video_link":"https:\/\/www.youtube.com\/watch?v=-1XTHgs1SNo","background_video_start":"2","background_video_end":"25","background_overlay_background":"classic","background_overlay_opacity":{"unit":"px","size":"","sizes":[]}},"elements":[{"id":"2a2c3ab3","settings":{"_column_size":"50"},"elements":[],"isInner":"1","elType":"column"},{"id":"e1f8711","settings":{"_column_size":"50"},"elements":[],"isInner":"1","elType":"column"}],"isInner":"1","elType":"section"}],"isInner":"","elType":"column"}],"isInner":"","elType":"section"},{"id":"6f8824c1","settings":{"structure":"20","content_width":{"unit":"px","size":"1224","sizes":[]},"content_position":"middle","margin":{"unit":"px","top":"0","right":"0","bottom":"80","left":"0","isLinked":""},"_element_id":"rh-about","margin_tablet":{"unit":"px","top":"40","right":"0","bottom":"40","left":"0","isLinked":"1"},"padding_tablet":{"unit":"px","top":"10","right":"10","bottom":"10","left":"10","isLinked":"1"},"margin_mobile":{"unit":"px","top":"40","right":"0","bottom":"10","left":"0","isLinked":""},"padding_tablet_extra":{"unit":"px","top":"0","right":"10","bottom":"0","left":"10","isLinked":""},"padding_laptop":{"unit":"px","top":"0","right":"10","bottom":"0","left":"10","isLinked":""},"padding":{"unit":"px","top":"130","right":"0","bottom":"0","left":"0","isLinked":""}},"elements":[{"id":"26305076","settings":{"_column_size":"50","content_position":"center"},"elements":[{"id":"4830c3ec","settings":{"title":"- About RealHomes","header_size":"span","__globals__":{"typography_typography":"","title_color":""},"title_color":"#3A7658","typography_typography":"custom","typography_font_family":"Archivo","typography_font_size":{"unit":"px","size":"16","sizes":[]},"typography_font_weight":"600","typography_line_height":{"unit":"px","size":"25","sizes":[]},"typography_word_spacing":{"unit":"em","size":"","sizes":[]}},"elements":[],"isInner":false,"widgetType":"heading","elType":"widget"},{"id":"3ae9eeda","settings":{"title":"Where Life Becomes Magical","__globals__":{"typography_typography":""},"title_color":"#0A1510","typography_typography":"custom","typography_font_family":"Archivo Black","typography_font_size":{"unit":"px","size":"64","sizes":[]},"typography_font_weight":"600","typography_line_height":{"unit":"px","size":"70","sizes":[]},"typography_font_size_tablet":{"unit":"px","size":"46","sizes":[]},"typography_line_height_tablet":{"unit":"em","size":"1.2","sizes":[]},"typography_font_size_mobile":{"unit":"px","size":"26","sizes":[]}},"elements":[],"isInner":false,"widgetType":"heading","elType":"widget"},{"id":"10c4c3d1","settings":{"width":{"unit":"px","size":"60","sizes":[]},"width_tablet":{"unit":"px","size":"","sizes":[]},"width_mobile":{"unit":"px","size":"","sizes":[]},"text":"Divider","color":"#3A7658","weight":{"unit":"px","size":"3","sizes":[]},"gap":{"unit":"px","size":"0","sizes":[]},"__globals__":{"color":""}},"elements":[],"isInner":false,"widgetType":"divider","elType":"widget"}],"isInner":"","elType":"column"},{"id":"42868690","settings":{"_column_size":"50","space_between_widgets":"0","content_position":"center"},"elements":[{"id":"67aa723f","settings":{"title":"Nestled in the tranquil lap of Skycity, RealHomes are 4 &amp; 5 BHK luxurious apartments and Duplex and Triplex storeyed, redefining the lifestyle. Being iconic towers in Skycity, this project offers a majestic view of the skyline.","header_size":"p","title_color":"#0A1510","typography_typography":"custom","typography_font_family":"Archivo","typography_font_size":{"unit":"px","size":"22","sizes":[]},"typography_font_weight":"400","typography_line_height":{"unit":"custom","size":"160%","sizes":[]},"typography_line_height_tablet":{"unit":"custom","size":"","sizes":[]},"typography_line_height_mobile":{"unit":"custom","size":"","sizes":[]},"_margin":{"unit":"px","top":"40","right":"0","bottom":"43","left":"0","isLinked":""},"_margin_tablet":{"unit":"px","top":"0","right":"0","bottom":"20","left":"0","isLinked":""}},"elements":[],"isInner":false,"widgetType":"heading","elType":"widget"},{"id":"2e63a88b","settings":{"text":"About Us","selected_icon":{"value":"fas fa-angle-right","library":"fa-solid"},"background_color":"#FFFFFF","__globals__":{"background_color":"","button_text_color":"","hover_color":""},"typography_typography":"custom","typography_font_family":"Archivo","typography_font_size":{"unit":"px","size":"18","sizes":[]},"typography_font_weight":"600","button_text_color":"#3A7658","hover_color":"#0A1510","typography_line_height_mobile":{"unit":"em","size":"1","sizes":[]},"_padding_mobile":{"unit":"px","top":"0","right":"0","bottom":"0","left":"0","isLinked":"1"},"icon_indent":{"unit":"px","size":"9","sizes":[]},"text_padding":{"unit":"px","top":"0","right":"0","bottom":"0","left":"0","isLinked":"1"}},"elements":[],"isInner":false,"widgetType":"button","elType":"widget"}],"isInner":"","elType":"column"}],"isInner":"","elType":"section"},{"id":"d61d305","settings":{"content_width":{"unit":"px","size":"1224","sizes":[]},"margin":{"unit":"px","top":"0","right":"0","bottom":"0","left":"0","isLinked":"1"},"padding_tablet":{"unit":"px","top":"10","right":"10","bottom":"10","left":"10","isLinked":"1"},"margin_tablet":{"unit":"px","top":"0","right":"0","bottom":"40","left":"0","isLinked":""},"margin_mobile":{"unit":"px","top":"0","right":"0","bottom":"20","left":"0","isLinked":""},"padding_tablet_extra":{"unit":"px","top":"0","right":"10","bottom":"0","left":"10","isLinked":""},"padding_laptop":{"unit":"px","top":"0","right":"10","bottom":"0","left":"10","isLinked":""}},"elements":[{"id":"1de9c7e3","settings":{"_column_size":"100"},"elements":[{"id":"67f2ba09","settings":{"revslidertitle":"Condo Slider","shortcode":"[rev_slider alias=\"condo-slider\" slidertitle=\"Condo Slider\"][\/rev_slider]"},"elements":[],"isInner":false,"widgetType":"slider_revolution","elType":"widget"}],"isInner":"","elType":"column"}],"isInner":"","elType":"section"},{"id":"7779eb17","settings":{"content_width":{"unit":"px","size":"1224","sizes":[]},"structure":"30","margin":{"unit":"px","top":"0","right":"0","bottom":"120","left":"0","isLinked":""},"_element_id":"rh-amenities","margin_tablet":{"unit":"px","top":"0","right":"0","bottom":"40","left":"0","isLinked":""},"margin_mobile":{"unit":"px","top":"","right":"0","bottom":"","left":"0","isLinked":"1"},"padding":{"unit":"px","top":"120","right":"0","bottom":"0","left":"0","isLinked":""},"padding_tablet":{"unit":"px","top":"0","right":"0","bottom":"0","left":"0","isLinked":"1"}},"elements":[{"id":"4cc1f6e","settings":{"_column_size":"33","text_align":"center","border_border":"none","border_width":{"unit":"px","top":"0","right":"1","bottom":"0","left":"0","isLinked":""},"border_color":"#0A151021","background_background":"classic","background_color":"#FFFFFF","background_hover_background":"classic","background_hover_color":"#8F8F8F40","__globals__":{"background_hover_color":""},"padding_mobile":{"unit":"px","top":"40","right":"0","bottom":"40","left":"0","isLinked":""}},"elements":[{"id":"114e5039","settings":{"title":"120","__globals__":{"typography_typography":""},"title_color":"#0A1510","typography_typography":"custom","typography_font_family":"Archivo Black","typography_font_size":{"unit":"px","size":"64","sizes":[]},"typography_font_weight":"400","typography_line_height":{"unit":"px","size":"70","sizes":[]},"typography_font_size_tablet":{"unit":"px","size":"48","sizes":[]}},"elements":[],"isInner":false,"widgetType":"heading","elType":"widget"},{"id":"538452b1","settings":{"width":{"unit":"px","size":"60","sizes":[]},"width_tablet":{"unit":"px","size":"","sizes":[]},"width_mobile":{"unit":"px","size":"","sizes":[]},"align":"center","text":"Divider","color":"#3A7658","weight":{"unit":"px","size":"3","sizes":[]},"gap":{"unit":"px","size":"0","sizes":[]},"__globals__":{"color":""}},"elements":[],"isInner":false,"widgetType":"divider","elType":"widget"},{"id":"6232fa64","settings":{"title":"Modern units spread <br>over twelve floors","__globals__":{"typography_typography":""},"title_color":"#0A1510","typography_typography":"custom","typography_font_family":"Archivo","typography_font_size":{"unit":"px","size":"22","sizes":[]},"typography_font_weight":"400","typography_line_height":{"unit":"px","size":"35","sizes":[]}},"elements":[],"isInner":false,"widgetType":"heading","elType":"widget"}],"isInner":"","elType":"column"},{"id":"5645f17d","settings":{"_column_size":"33","text_align":"center","border_border":"solid","border_width":{"unit":"px","top":"0","right":"1","bottom":"0","left":"1","isLinked":""},"border_color":"#0A151021","background_hover_background":"classic","background_hover_color":"#8F8F8F40","padding_mobile":{"unit":"px","top":"40","right":"0","bottom":"40","left":"0","isLinked":""}},"elements":[{"id":"77dd2691","settings":{"title":"7.5k","__globals__":{"typography_typography":""},"title_color":"#0A1510","typography_typography":"custom","typography_font_family":"Archivo Black","typography_font_size":{"unit":"px","size":"64","sizes":[]},"typography_font_weight":"400","typography_line_height":{"unit":"px","size":"70","sizes":[]},"typography_font_size_tablet":{"unit":"px","size":"48","sizes":[]}},"elements":[],"isInner":false,"widgetType":"heading","elType":"widget"},{"id":"536db32b","settings":{"width":{"unit":"px","size":"60","sizes":[]},"width_tablet":{"unit":"px","size":"","sizes":[]},"width_mobile":{"unit":"px","size":"","sizes":[]},"align":"center","text":"Divider","color":"#3A7658","weight":{"unit":"px","size":"3","sizes":[]},"gap":{"unit":"px","size":"0","sizes":[]},"__globals__":{"color":""}},"elements":[],"isInner":false,"widgetType":"divider","elType":"widget"},{"id":"7069bd0d","settings":{"title":"Square Feet of nature<br> around the block","__globals__":{"typography_typography":""},"title_color":"#0A1510","typography_typography":"custom","typography_font_family":"Archivo","typography_font_size":{"unit":"px","size":"22","sizes":[]},"typography_font_weight":"400","typography_line_height":{"unit":"px","size":"35","sizes":[]}},"elements":[],"isInner":false,"widgetType":"heading","elType":"widget"}],"isInner":"","elType":"column"},{"id":"14facb82","settings":{"_column_size":"33","text_align":"center","background_hover_background":"classic","background_hover_color":"#8F8F8F40","padding_mobile":{"unit":"px","top":"20","right":"0","bottom":"20","left":"0","isLinked":""}},"elements":[{"id":"21283ee1","settings":{"title":"60+","__globals__":{"typography_typography":""},"title_color":"#0A1510","typography_typography":"custom","typography_font_family":"Archivo Black","typography_font_size":{"unit":"px","size":"64","sizes":[]},"typography_font_weight":"400","typography_line_height":{"unit":"px","size":"70","sizes":[]},"typography_font_size_tablet":{"unit":"px","size":"48","sizes":[]}},"elements":[],"isInner":false,"widgetType":"heading","elType":"widget"},{"id":"2878c23","settings":{"width":{"unit":"px","size":"60","sizes":[]},"width_tablet":{"unit":"px","size":"","sizes":[]},"width_mobile":{"unit":"px","size":"","sizes":[]},"align":"center","text":"Divider","color":"#3A7658","weight":{"unit":"px","size":"3","sizes":[]},"gap":{"unit":"px","size":"0","sizes":[]},"__globals__":{"color":""}},"elements":[],"isInner":false,"widgetType":"divider","elType":"widget"},{"id":"2e21aebc","settings":{"title":"Parking spaces for<br> residents and guests","__globals__":{"typography_typography":""},"title_color":"#0A1510","typography_typography":"custom","typography_font_family":"Archivo","typography_font_size":{"unit":"px","size":"22","sizes":[]},"typography_font_weight":"400","typography_line_height":{"unit":"px","size":"35","sizes":[]}},"elements":[],"isInner":false,"widgetType":"heading","elType":"widget"}],"isInner":"","elType":"column"}],"isInner":"","elType":"section"},{"id":"77351970","settings":{"layout":"full_width","gap":"no","column_position":"top","stretch_section":"section-stretched","structure":"20","margin":{"unit":"px","top":"0","right":"0","bottom":"0","left":"0","isLinked":"1"},"margin_tablet":{"unit":"px","top":"0","right":"0","bottom":"0","left":"0","isLinked":""}},"elements":[{"id":"11c4af7f","settings":{"_column_size":"50","space_between_widgets":"0","background_background":"classic","background_image":{"url":"https:\/\/ultra.inspirylabs.com\/condominium\/wp-content\/uploads\/sites\/8\/2023\/04\/way-to-live.jpg","id":"1090","size":"","alt":"","source":"library"},"background_position":"center center","background_repeat":"no-repeat","background_size":"cover","border_width":{"unit":"px","top":"0","right":"0","bottom":"0","left":"0","isLinked":"1"},"margin":{"unit":"px","top":"0","right":"0","bottom":"0","left":"0","isLinked":""},"padding":{"unit":"px","top":"0","right":"0","bottom":"0","left":"0","isLinked":""},"_inline_size_tablet":"100","padding_tablet":{"unit":"%","top":"0","right":"0","bottom":"0","left":"0","isLinked":""},"padding_mobile":{"unit":"%","top":"","right":"","bottom":"","left":"","isLinked":"1"},"hide_tablet":"hidden-tablet","hide_mobile":"hidden-mobile","_inline_size_tablet_extra":"100","hide_tablet_extra":"hidden-tablet_extra","background_slideshow_gallery":[{"id":"964","url":"https:\/\/ultra.inspirylabs.com\/condominium\/wp-content\/uploads\/sites\/8\/2023\/05\/spacejoy-77U1wzOD1yw-unsplash-2.jpg"},{"id":"965","url":"https:\/\/ultra.inspirylabs.com\/condominium\/wp-content\/uploads\/sites\/8\/2023\/05\/spacejoy-XpbtQfr9Skg-unsplash.jpg"}],"background_slideshow_transition_duration":"2000","background_slideshow_background_size":"cover","background_slideshow_background_position":"center center","background_slideshow_ken_burns":"yes","background_slideshow_ken_burns_zoom_direction":"out"},"elements":[],"isInner":"","elType":"column"},{"id":"19bafb5a","settings":{"_column_size":"50","background_background":"classic","background_color":"#0A1510","padding":{"unit":"px","top":"70","right":"100","bottom":"70","left":"100","isLinked":""},"_inline_size_tablet":"100","padding_tablet":{"unit":"px","top":"60","right":"20","bottom":"60","left":"20","isLinked":""},"padding_mobile":{"unit":"px","top":"60","right":"20","bottom":"60","left":"20","isLinked":""},"_inline_size_tablet_extra":"100","padding_laptop":{"unit":"px","top":"60","right":"60","bottom":"60","left":"60","isLinked":"1"}},"elements":[{"id":"1a7ef46e","settings":{"title":"- Amenities","header_size":"span","title_color":"#FFFFFF","__globals__":{"typography_typography":"","title_color":""},"typography_typography":"custom","typography_font_family":"Archivo","typography_font_size":{"unit":"px","size":"16","sizes":[]},"typography_font_weight":"600","typography_line_height":{"unit":"px","size":"25","sizes":[]},"typography_word_spacing":{"unit":"em","size":"","sizes":[]}},"elements":[],"isInner":false,"widgetType":"heading","elType":"widget"},{"id":"379f4455","settings":{"title":"A New Way to Live","title_color":"#FFFFFF","_margin":{"unit":"px","top":"0","right":"0","bottom":"20","left":"0","isLinked":""},"__globals__":{"typography_typography":""},"typography_typography":"custom","typography_font_family":"Archivo Black","typography_font_size":{"unit":"px","size":"64","sizes":[]},"typography_font_weight":"600","typography_line_height":{"unit":"px","size":"70","sizes":[]},"typography_font_size_mobile":{"unit":"px","size":"26","sizes":[]},"typography_line_height_mobile":{"unit":"em","size":"1.2","sizes":[]},"_margin_mobile":{"unit":"px","top":"0","right":"0","bottom":"0","left":"0","isLinked":""}},"elements":[],"isInner":false,"widgetType":"heading","elType":"widget"},{"id":"33ff86b5","settings":{"width":{"unit":"px","size":"60","sizes":[]},"width_tablet":{"unit":"px","size":"","sizes":[]},"width_mobile":{"unit":"px","size":"","sizes":[]},"align":"left","text":"Divider","color":"#FFFFFF","weight":{"unit":"px","size":"3","sizes":[]},"gap":{"unit":"px","size":"0","sizes":[]},"_margin":{"unit":"px","top":"-12","right":"0","bottom":"0","left":"0","isLinked":""},"__globals__":{"color":""}},"elements":[],"isInner":false,"widgetType":"divider","elType":"widget"},{"id":"2bdbcada","settings":{"title":"The RealHomes is a condo in Asheville, NC. The land around it was left untouched, and the surrounding apartments are built from sustainable materials.","header_size":"p","title_color":"#FFFFFF","typography_typography":"custom","typography_font_family":"Archivo","typography_font_size":{"unit":"px","size":"22","sizes":[]},"typography_font_weight":"400","typography_line_height":{"unit":"custom","size":"160%","sizes":[]},"typography_line_height_tablet":{"unit":"custom","size":"","sizes":[]},"typography_line_height_mobile":{"unit":"custom","size":"","sizes":[]},"_margin":{"unit":"px","top":"0","right":"0","bottom":"20","left":"0","isLinked":""}},"elements":[],"isInner":false,"widgetType":"heading","elType":"widget"},{"id":"4801e4f5","settings":{"icon_list":[{"text":"High End Furniture","selected_icon":{"value":{"url":"https:\/\/ultra.inspirylabs.com\/condominium\/wp-content\/uploads\/sites\/8\/2023\/04\/sofa.svg","id":"380"},"library":"svg"},"_id":"e18a7de"},{"text":"24 Floors","selected_icon":{"value":{"url":"https:\/\/ultra.inspirylabs.com\/condominium\/wp-content\/uploads\/sites\/8\/2023\/04\/building.svg","id":"379"},"library":"svg"},"_id":"4ca45f3"},{"text":"Natural Lighting","selected_icon":{"value":{"url":"https:\/\/ultra.inspirylabs.com\/condominium\/wp-content\/uploads\/sites\/8\/2023\/04\/sun.svg","id":"382"},"library":"svg"},"_id":"a067ebc"},{"text":"Solar Heating","selected_icon":{"value":{"url":"https:\/\/ultra.inspirylabs.com\/condominium\/wp-content\/uploads\/sites\/8\/2023\/04\/solar-heating.svg","id":"390"},"library":"svg"},"_id":"5dfab1d"},{"text":"Pet Friendly","selected_icon":{"value":{"url":"https:\/\/ultra.inspirylabs.com\/condominium\/wp-content\/uploads\/sites\/8\/2023\/04\/pet-friendly.svg","id":"389"},"library":"svg"},"_id":"e7346f1"},{"text":"Hydromassage Bathrooms","selected_icon":{"value":{"url":"https:\/\/ultra.inspirylabs.com\/condominium\/wp-content\/uploads\/sites\/8\/2023\/04\/tub.svg","id":"388"},"library":"svg"},"_id":"eec0a14"},{"text":"Low Energy Tools","selected_icon":{"value":{"url":"https:\/\/ultra.inspirylabs.com\/condominium\/wp-content\/uploads\/sites\/8\/2023\/04\/energy.svg","id":"387"},"library":"svg"},"_id":"be38003"},{"text":"Average size 1,258 Sq Ft","selected_icon":{"value":{"url":"https:\/\/ultra.inspirylabs.com\/condominium\/wp-content\/uploads\/sites\/8\/2023\/04\/area.svg","id":"386"},"library":"svg"},"_id":"40adca5"}],"space_between":{"unit":"px","size":"15","sizes":[]},"icon_color":"#2E5E46","text_color":"#FFFFFF","space_between_widescreen":{"unit":"px","size":"","sizes":[]},"icon_align_widescreen":"","icon_size_widescreen":{"unit":"px","size":"","sizes":[]},"icon_self_align_widescreen":"","icon_self_vertical_align_widescreen":"","icon_vertical_offset_widescreen":{"unit":"px","size":"","sizes":[]},"icon_typography_font_size_widescreen":{"unit":"px","size":"","sizes":[]},"icon_typography_line_height_widescreen":{"unit":"px","size":"","sizes":[]},"icon_typography_letter_spacing_widescreen":{"unit":"px","size":"","sizes":[]},"icon_typography_word_spacing_widescreen":{"unit":"px","size":"","sizes":[]},"_margin_widescreen":{"unit":"px","top":"","right":"","bottom":"","left":"","isLinked":"1"},"_margin_mobile_extra":{"unit":"px","top":"","right":"","bottom":"","left":"","isLinked":"1"},"_padding_widescreen":{"unit":"px","top":"","right":"","bottom":"","left":"","isLinked":"1"},"_padding_mobile_extra":{"unit":"px","top":"","right":"","bottom":"","left":"","isLinked":"1"},"_element_width_widescreen":"","_element_custom_width_widescreen":{"unit":"px","size":"","sizes":[]},"_element_vertical_align_widescreen":"","_offset_x_widescreen":{"unit":"px","size":"","sizes":[]},"_offset_x_end_widescreen":{"unit":"px","size":"","sizes":[]},"_offset_y_widescreen":{"unit":"px","size":"","sizes":[]},"_offset_y_end_widescreen":{"unit":"px","size":"","sizes":[]},"_z_index_widescreen":"","_animation_widescreen":"","_transform_rotateZ_effect_widescreen":{"unit":"deg","size":"","sizes":[]},"_transform_rotateX_effect_widescreen":{"unit":"deg","size":"","sizes":[]},"_transform_rotateY_effect_widescreen":{"unit":"deg","size":"","sizes":[]},"_transform_perspective_effect_widescreen":{"unit":"px","size":"","sizes":[]},"_transform_translateX_effect_widescreen":{"unit":"px","size":"","sizes":[]},"_transform_translateY_effect_widescreen":{"unit":"px","size":"","sizes":[]},"_transform_scale_effect_widescreen":{"unit":"px","size":"","sizes":[]},"_transform_scaleX_effect_widescreen":{"unit":"px","size":"","sizes":[]},"_transform_scaleY_effect_widescreen":{"unit":"px","size":"","sizes":[]},"_transform_skewX_effect_widescreen":{"unit":"deg","size":"","sizes":[]},"_transform_skewY_effect_widescreen":{"unit":"deg","size":"","sizes":[]},"_transform_rotateZ_effect_hover_widescreen":{"unit":"deg","size":"","sizes":[]},"_transform_rotateX_effect_hover_widescreen":{"unit":"deg","size":"","sizes":[]},"_transform_rotateY_effect_hover_widescreen":{"unit":"deg","size":"","sizes":[]},"_transform_perspective_effect_hover_widescreen":{"unit":"px","size":"","sizes":[]},"_transform_translateX_effect_hover_widescreen":{"unit":"px","size":"","sizes":[]},"_transform_translateY_effect_hover_widescreen":{"unit":"px","size":"","sizes":[]},"_transform_scale_effect_hover_widescreen":{"unit":"px","size":"","sizes":[]},"_transform_scaleX_effect_hover_widescreen":{"unit":"px","size":"","sizes":[]},"_transform_scaleY_effect_hover_widescreen":{"unit":"px","size":"","sizes":[]},"_transform_skewX_effect_hover_widescreen":{"unit":"deg","size":"","sizes":[]},"_transform_skewY_effect_hover_widescreen":{"unit":"deg","size":"","sizes":[]},"motion_fx_transform_x_anchor_point_widescreen":"","motion_fx_transform_y_anchor_point_widescreen":"","_background_image_widescreen":{"url":"","id":"","size":""},"_background_position_widescreen":"","_background_xpos_widescreen":{"unit":"px","size":"","sizes":[]},"_background_ypos_widescreen":{"unit":"px","size":"","sizes":[]},"_background_repeat_widescreen":"","_background_size_widescreen":"","_background_bg_width_widescreen":{"unit":"px","size":"","sizes":[]},"_background_slideshow_background_size_widescreen":"","_background_slideshow_background_position_widescreen":"","_background_hover_image_widescreen":{"url":"","id":"","size":""},"_background_hover_position_widescreen":"","_background_hover_xpos_widescreen":{"unit":"px","size":"","sizes":[]},"_background_hover_ypos_widescreen":{"unit":"px","size":"","sizes":[]},"_background_hover_repeat_widescreen":"","_background_hover_size_widescreen":"","_background_hover_bg_width_widescreen":{"unit":"px","size":"","sizes":[]},"_background_hover_slideshow_background_size_widescreen":"","_background_hover_slideshow_background_position_widescreen":"","_border_width_widescreen":{"unit":"px","top":"","right":"","bottom":"","left":"","isLinked":"1"},"_border_width_mobile_extra":{"unit":"px","top":"","right":"","bottom":"","left":"","isLinked":"1"},"_border_radius_widescreen":{"unit":"px","top":"","right":"","bottom":"","left":"","isLinked":"1"},"_border_radius_mobile_extra":{"unit":"px","top":"","right":"","bottom":"","left":"","isLinked":"1"},"_border_hover_width_widescreen":{"unit":"px","top":"","right":"","bottom":"","left":"","isLinked":"1"},"_border_hover_width_mobile_extra":{"unit":"px","top":"","right":"","bottom":"","left":"","isLinked":"1"},"_border_radius_hover_widescreen":{"unit":"px","top":"","right":"","bottom":"","left":"","isLinked":"1"},"_border_radius_hover_mobile_extra":{"unit":"px","top":"","right":"","bottom":"","left":"","isLinked":"1"},"_mask_size_widescreen":"","_mask_size_scale_widescreen":{"unit":"px","size":"","sizes":[]},"_mask_position_widescreen":"","_mask_position_x_widescreen":{"unit":"px","size":"","sizes":[]},"_mask_position_y_widescreen":{"unit":"px","size":"","sizes":[]},"_mask_repeat_widescreen":"","hide_widescreen":"","icon_typography_typography":"custom","icon_typography_font_family":"Roboto","icon_typography_font_size":{"unit":"px","size":"18","sizes":[]},"icon_typography_font_weight":"400","icon_size":{"unit":"px","size":"20","sizes":[]},"text_color_hover":"#3A7658","__globals__":{"text_color_hover":""}},"elements":[],"isInner":false,"widgetType":"icon-list","elType":"widget"}],"isInner":"","elType":"column"}],"isInner":"","elType":"section"},{"id":"6f1236","settings":{"margin":{"unit":"px","top":"0","right":"0","bottom":"60","left":"0","isLinked":""},"_element_id":"rh-features","content_width":{"unit":"px","size":"750","sizes":[]},"margin_tablet":{"unit":"px","top":"40","right":"0","bottom":"20","left":"0","isLinked":""},"margin_mobile":{"unit":"px","top":"40","right":"0","bottom":"20","left":"0","isLinked":""},"padding_mobile":{"unit":"px","top":"0","right":"10","bottom":"0","left":"10","isLinked":""},"padding":{"unit":"px","top":"140","right":"0","bottom":"0","left":"0","isLinked":""},"padding_tablet":{"unit":"px","top":"0","right":"0","bottom":"0","left":"0","isLinked":"1"}},"elements":[{"id":"802a4cf","settings":{"_column_size":"100"},"elements":[{"id":"7f766a2","settings":{"title":"Kind to Both -\nNature &amp; People","align":"center","__globals__":{"typography_typography":""},"title_color":"#0A1510","typography_typography":"custom","typography_font_family":"Archivo Black","typography_font_size":{"unit":"px","size":"64","sizes":[]},"typography_font_weight":"600","typography_line_height":{"unit":"px","size":"70","sizes":[]},"typography_font_size_tablet":{"unit":"px","size":"46","sizes":[]},"typography_font_size_mobile":{"unit":"px","size":"26","sizes":[]},"typography_line_height_tablet":{"unit":"em","size":"1.3","sizes":[]}},"elements":[],"isInner":false,"widgetType":"heading","elType":"widget"},{"id":"6333fb6b","settings":{"width":{"unit":"px","size":"100","sizes":[]},"width_tablet":{"unit":"px","size":"","sizes":[]},"width_mobile":{"unit":"px","size":"","sizes":[]},"align":"center","text":"Divider","color":"#3A7658","weight":{"unit":"px","size":"3","sizes":[]},"gap":{"unit":"px","size":"0","sizes":[]},"__globals__":{"color":""}},"elements":[],"isInner":false,"widgetType":"divider","elType":"widget"}],"isInner":"","elType":"column"}],"isInner":"","elType":"section"},{"id":"6a2ebc10","settings":{"content_width":{"unit":"px","size":"1224","sizes":[]},"structure":"20","margin":{"unit":"px","top":"0","right":"0","bottom":"0","left":"0","isLinked":"1"},"layout":"full_width","content_position":"middle","padding_tablet":{"unit":"px","top":"0","right":"20","bottom":"0","left":"20","isLinked":""},"margin_tablet":{"unit":"px","top":"0","right":"0","bottom":"40","left":"0","isLinked":""},"padding":{"unit":"px","top":"0","right":"0","bottom":"0","left":"0","isLinked":""},"padding_tablet_extra":{"unit":"px","top":"0","right":"20","bottom":"0","left":"20","isLinked":""}},"elements":[{"id":"44918649","settings":{"_column_size":"50","_inline_size":"45","padding":{"unit":"px","top":"0","right":"80","bottom":"0","left":"0","isLinked":""},"align":"flex-end","_inline_size_tablet":"100","padding_tablet":{"unit":"px","top":"0","right":"0","bottom":"0","left":"0","isLinked":"1"},"margin_tablet":{"unit":"px","top":"0","right":"0","bottom":"0","left":"0","isLinked":""}},"elements":[{"id":"5f6b025c","settings":{"tabs":[{"tab_title":"Energy Efficient Technology","tab_content":"<p>Embrace sustainability with smart insulation, LED lighting, and energy-efficient appliances for a greener living experience.<\/p>","_id":"07c6769","selected_icon":{"value":{"url":"https:\/\/ultra.inspirylabs.com\/condominium\/wp-content\/uploads\/sites\/8\/2023\/04\/energy-efficient.svg","id":"74"},"library":"svg"},"selected_active_icon":{"value":{"url":"https:\/\/ultra.inspirylabs.com\/condominium\/wp-content\/uploads\/sites\/8\/2023\/04\/energy-efficient-active.svg","id":"75"},"library":"svg"}},{"tab_title":"Green Roofs","tab_content":"<p>Our condominium feature innovative green roofs, creating a harmonious blend of nature and urban living.<\/p>","selected_icon":{"value":{"url":"https:\/\/ultra.inspirylabs.com\/condominium\/wp-content\/uploads\/sites\/8\/2023\/04\/green-roofs.svg","id":"76"},"library":"svg"},"selected_active_icon":{"value":{"url":"https:\/\/ultra.inspirylabs.com\/condominium\/wp-content\/uploads\/sites\/8\/2023\/04\/green-roofs-active.svg","id":"77"},"library":"svg"},"_id":"ac7d39c"},{"tab_title":"Natural Materials","tab_content":"<p>Adorned with natural materials like responsibly sourced wood and stone accents, blending modern design with organic beauty.<\/p>","selected_icon":{"value":{"url":"https:\/\/ultra.inspirylabs.com\/condominium\/wp-content\/uploads\/sites\/8\/2023\/04\/natural-materials.svg","id":"78"},"library":"svg"},"selected_active_icon":{"value":{"url":"https:\/\/ultra.inspirylabs.com\/condominium\/wp-content\/uploads\/sites\/8\/2023\/04\/natural-materials-active.svg","id":"79"},"library":"svg"},"_id":"527dff4"},{"tab_title":"Water Preservation","tab_content":"<p>Experience our dedication to water preservation through innovative technologies and practices, ensuring a sustainable and eco-friendly living environment.<\/p>","selected_icon":{"value":{"url":"https:\/\/ultra.inspirylabs.com\/condominium\/wp-content\/uploads\/sites\/8\/2023\/04\/water-preservation.svg","id":"82"},"library":"svg"},"selected_active_icon":{"value":{"url":"https:\/\/ultra.inspirylabs.com\/condominium\/wp-content\/uploads\/sites\/8\/2023\/04\/water-preservation-active.svg","id":"83"},"library":"svg"},"_id":"22cc75b"},{"tab_title":"Protecting Biodiversity","tab_content":"<p>Through conscious planning and sustainable landscaping, we create a nurturing habitat for diverse flora and fauna.<\/p>","selected_icon":{"value":{"url":"https:\/\/ultra.inspirylabs.com\/condominium\/wp-content\/uploads\/sites\/8\/2023\/04\/protecting-bio-diversity.svg","id":"80"},"library":"svg"},"selected_active_icon":{"value":{"url":"https:\/\/ultra.inspirylabs.com\/condominium\/wp-content\/uploads\/sites\/8\/2023\/04\/protecting-bio-diversity-active.svg","id":"81"},"library":"svg"},"_id":"08a5b0f"}],"icon_align":"","icon_bg_color":"#F2F2F2","icon_padding":{"unit":"px","top":"5","right":"5","bottom":"5","left":"5","isLinked":"1"},"title_typography_typography":"custom","title_typography_font_family":"Archivo Black","title_typography_font_size":{"unit":"px","size":"22","sizes":[]},"title_typography_font_weight":"400","title_typography_line_height":{"unit":"custom","size":"150%","sizes":[]},"title_color":"#0A1510","tab_active_color":"#3A7658","title_padding":{"unit":"px","top":"20","right":"0","bottom":"20","left":"4","isLinked":""},"content_typography_typography":"custom","content_typography_font_family":"Archivo","content_typography_font_size":{"unit":"px","size":"16","sizes":[]},"content_typography_font_weight":"400","content_typography_line_height":{"unit":"px","size":"25","sizes":[]},"content_color":"#0A151091","content_padding":{"unit":"px","top":"0","right":"0","bottom":"32","left":"65","isLinked":""},"__globals__":{"title_typography_typography":""},"_element_width":"initial","_element_custom_width":{"unit":"px","size":"410","sizes":[]},"_element_custom_width_tablet":{"unit":"%","size":"100","sizes":[]},"_element_custom_width_mobile":{"unit":"%","size":"","sizes":[]},"title_typography_font_size_mobile":{"unit":"px","size":"18","sizes":[]},"title_typography_line_height_mobile":{"unit":"em","size":"1.2","sizes":[]},"content_padding_mobile":{"unit":"px","top":"20","right":"0","bottom":"20","left":"0","isLinked":""},"title_typography_line_height_tablet_extra":{"unit":"em","size":"","sizes":[]}},"elements":[],"isInner":false,"widgetType":"inspiry-accordion-widget","elType":"widget"}],"isInner":"","elType":"column"},{"id":"7b9447c8","settings":{"_column_size":"50","_inline_size":"55","_inline_size_tablet":"100","padding_tablet":{"unit":"px","top":"0","right":"0","bottom":"0","left":"0","isLinked":"1"},"space_between_widgets":"0","padding":{"unit":"px","top":"0","right":"0","bottom":"0","left":"0","isLinked":"1"}},"elements":[{"id":"21b6ac9f","settings":{"carousel":[{"id":"1091","url":"https:\/\/ultra.inspirylabs.com\/condominium\/wp-content\/uploads\/sites\/8\/2023\/04\/kind-to-nature.jpg"},{"id":"1092","url":"https:\/\/ultra.inspirylabs.com\/condominium\/wp-content\/uploads\/sites\/8\/2023\/04\/kind-to-people.jpg"}],"thumbnail_size":"post-featured-image","image_carousel_radius":{"unit":"px","top":"0","right":"0","bottom":"0","left":"0","isLinked":"1"},"navigation":"arrows","arrows_navigation_wrapper_width":"inline","arrows_align":"left","arrows_vertical_align":"bottom","slides_to_show":"1","effect":"fade","speed":"2000"},"elements":[],"isInner":false,"widgetType":"inspiry-image-carousel-widget","elType":"widget"}],"isInner":"","elType":"column"}],"isInner":"","elType":"section"},{"id":"305ed8a0","settings":{"structure":"20","content_width":{"unit":"px","size":"1224","sizes":[]},"content_position":"middle","margin":{"unit":"px","top":"0","right":"0","bottom":"80","left":"0","isLinked":""},"_element_id":"rh-floor-plans","margin_tablet":{"unit":"px","top":"0","right":"0","bottom":"40","left":"0","isLinked":""},"padding_tablet":{"unit":"px","top":"0","right":"10","bottom":"0","left":"10","isLinked":""},"padding_tablet_extra":{"unit":"px","top":"0","right":"10","bottom":"0","left":"10","isLinked":""},"padding_laptop":{"unit":"px","top":"0","right":"10","bottom":"0","left":"10","isLinked":""},"padding":{"unit":"px","top":"120","right":"0","bottom":"0","left":"0","isLinked":""}},"elements":[{"id":"500fcdb","settings":{"_column_size":"50"},"elements":[{"id":"694c99e4","settings":{"title":"- Floor Plans","header_size":"span","__globals__":{"typography_typography":"","title_color":""},"title_color":"#3A7658","typography_typography":"custom","typography_font_family":"Archivo","typography_font_size":{"unit":"px","size":"16","sizes":[]},"typography_font_weight":"600","typography_line_height":{"unit":"px","size":"25","sizes":[]},"typography_word_spacing":{"unit":"em","size":"","sizes":[]}},"elements":[],"isInner":false,"widgetType":"heading","elType":"widget"},{"id":"24630016","settings":{"title":"Check Real<br>Homes<br>Apartments","__globals__":{"typography_typography":""},"title_color":"#0A1510","typography_typography":"custom","typography_font_family":"Archivo Black","typography_font_size":{"unit":"px","size":"64","sizes":[]},"typography_font_weight":"600","typography_line_height":{"unit":"px","size":"70","sizes":[]},"typography_font_size_tablet":{"unit":"px","size":"46","sizes":[]},"typography_font_size_mobile":{"unit":"px","size":"26","sizes":[]},"typograhpy_line_height_tablet":{"unit":"em","size":"1.2","sizes":[]},"typography_line_height_mobile":{"unit":"custom","size":"1.3","sizes":[]}},"elements":[],"isInner":false,"widgetType":"heading","elType":"widget"},{"id":"5a5c9615","settings":{"width":{"unit":"px","size":"60","sizes":[]},"width_tablet":{"unit":"px","size":"","sizes":[]},"width_mobile":{"unit":"px","size":"","sizes":[]},"align":"left","text":"Divider","color":"#3A7658","weight":{"unit":"px","size":"3","sizes":[]},"gap":{"unit":"px","size":"0","sizes":[]},"__globals__":{"color":""}},"elements":[],"isInner":false,"widgetType":"divider","elType":"widget"}],"isInner":"","elType":"column"},{"id":"85466aa","settings":{"_column_size":"50","content_position":"center"},"elements":[{"id":"566664af","settings":{"title":"The Real Homes is a home buyers dream. It's a condo in the nature, with beautiful views, lots of trees and plants, and a few big rocks here and there.","header_size":"p","title_color":"#0A1510","typography_typography":"custom","typography_font_family":"Archivo","typography_font_size":{"unit":"px","size":"22","sizes":[]},"typography_font_weight":"400","typography_line_height":{"unit":"custom","size":"160%","sizes":[]},"typography_line_height_tablet":{"unit":"custom","size":"","sizes":[]},"typography_line_height_mobile":{"unit":"custom","size":"","sizes":[]},"_margin":{"unit":"px","top":"0","right":"0","bottom":"0","left":"0","isLinked":""}},"elements":[],"isInner":false,"widgetType":"heading","elType":"widget"}],"isInner":"","elType":"column"}],"isInner":"","elType":"section"},{"id":"5498767a","settings":{"layout":"full_width","margin":{"unit":"px","top":"0","right":"0","bottom":"0","left":"0","isLinked":"1"},"margin_tablet":{"unit":"px","top":"0","right":"0","bottom":"40","left":"0","isLinked":""},"padding_tablet":{"unit":"px","top":"0","right":"20","bottom":"0","left":"20","isLinked":""},"gap":"no","padding_tablet_extra":{"unit":"px","top":"0","right":"0","bottom":"0","left":"0","isLinked":""}},"elements":[{"id":"2db820cc","settings":{"_column_size":"100"},"elements":[{"id":"69c7cbd5","settings":{"floor_plans_list":[{"fp_title":"Three Bedrooms","fp_price":"From $2,10,000","fp_beds":"3","fp_baths":"3","fp_area":" 654 sq ft","fp_image":{"url":"https:\/\/ultra.inspirylabs.com\/condominium\/wp-content\/uploads\/sites\/8\/2023\/04\/apartment-1.jpg","id":"1094","size":"","alt":"","source":"library"},"_id":"6a103cc","fp_lightbox_image":{"url":"https:\/\/ultra.inspirylabs.com\/condominium\/wp-content\/uploads\/sites\/8\/2023\/04\/1Bedroom-2d.jpg","id":"394","size":"","alt":"","source":"library"},"fp_description":"Experience the ultimate in luxury living with our stunning 3-bed condominiums. Located in the heart of the city, our modern and stylish units are designed to provide you with the utmost comfort and convenience."},{"fp_title":"Four Bedrooms","fp_price":"From $2,90,000","fp_beds":"4","fp_baths":"4","fp_area":" 1880 sq ft","fp_image":{"url":"https:\/\/ultra.inspirylabs.com\/condominium\/wp-content\/uploads\/sites\/8\/2023\/04\/apartment-2.jpg","id":"1095","size":"","alt":"","source":"library"},"_id":"88920e3","fp_lightbox_image":{"url":"https:\/\/ultra.inspirylabs.com\/condominium\/wp-content\/uploads\/sites\/8\/2023\/04\/2Bedroom-2d.jpg","id":"396","size":"","alt":"","source":"library"},"fp_description":"Experience the ultimate in luxury living with our stunning 4-bed condominiums. Located in the heart of the city, our modern and stylish units are designed to provide you with the utmost comfort and convenience."},{"fp_title":"Five Bedrooms","fp_price":"From $3,70,000","fp_beds":"5","fp_baths":"5","fp_area":" 2440 sq ft","fp_image":{"url":"https:\/\/ultra.inspirylabs.com\/condominium\/wp-content\/uploads\/sites\/8\/2023\/04\/apartment-3.jpg","id":"1096","size":"","alt":"","source":"library"},"_id":"d3ff2c6","fp_lightbox_image":{"url":"https:\/\/ultra.inspirylabs.com\/condominium\/wp-content\/uploads\/sites\/8\/2023\/04\/4Bedrooms-2d.jpg","id":"395","size":"","alt":"","source":"library"},"fp_description":"Experience the ultimate in luxury living with our stunning 5-bed condominiums. Located in the heart of the city, our modern and stylish units are designed to provide you with the utmost comfort and convenience."}],"floor_plans_columns":"three_col","floor_plan_image_size_custom_dimension":{"width":"500","height":"600"},"title_typography_typography":"custom","title_typography_font_family":"Archivo Black","title_typography_font_size":{"unit":"px","size":"40","sizes":[]},"title_typography_font_weight":"400","title_typography_line_height":{"unit":"custom","size":"1.2","sizes":[]},"title_typography_line_height_tablet":{"unit":"custom","size":"","sizes":[]},"title_typography_line_height_mobile":{"unit":"custom","size":"","sizes":[]},"fp_button_text":"View Floor Plan","contents_hover_height":{"unit":"px","size":"189","sizes":[]},"__globals__":{"title_typography_typography":""},"price_typography_typography":"custom","price_typography_font_family":"Archivo","price_typography_font_size":{"unit":"px","size":"22","sizes":[]},"price_typography_font_weight":"300","price_typography_line_height":{"unit":"px","size":"35","sizes":[]},"meta_typography_typography":"custom","meta_typography_font_family":"Archivo","meta_typography_font_size":{"unit":"px","size":"22","sizes":[]},"meta_typography_font_weight":"300","meta_typography_line_height":{"unit":"px","size":"35","sizes":[]},"button_typography_typography":"custom","button_typography_font_family":"Archivo","button_typography_font_size":{"unit":"px","size":"18","sizes":[]},"button_typography_font_weight":"600","button_typography_line_height":{"unit":"custom","size":"100%","sizes":[]},"title_typography_font_size_mobile":{"unit":"px","size":"26","sizes":[]},"title_bottom_margin":{"unit":"px","size":"10","sizes":[]},"price_margin":{"unit":"px","size":"10","sizes":[]},"contents_hover_height_mobile":{"unit":"px","size":"166","sizes":[]},"bedroom_icon":{"value":{"url":"https:\/\/ultra.inspirylabs.com\/condominium\/wp-content\/uploads\/sites\/8\/2023\/05\/bedroom-1-1.svg","id":"598"},"library":"svg"},"bathroom_icon":{"value":{"url":"https:\/\/ultra.inspirylabs.com\/condominium\/wp-content\/uploads\/sites\/8\/2023\/05\/shower-1.svg","id":"599"},"library":"svg"},"area_icon":{"value":{"url":"https:\/\/ultra.inspirylabs.com\/condominium\/wp-content\/uploads\/sites\/8\/2023\/05\/area-con.svg","id":"612"},"library":"svg"},"svg_icons_size":{"unit":"px","size":"","sizes":[]},"button_typography_line_height_laptop":{"unit":"custom","size":"","sizes":[]},"button_typography_line_height_tablet_extra":{"unit":"custom","size":"","sizes":[]},"button_typography_line_height_tablet":{"unit":"custom","size":"","sizes":[]},"button_typography_line_height_mobile":{"unit":"custom","size":"","sizes":[]},"button_type":"slide-in-left","view_button_margin":{"unit":"px","top":"10","right":"0","bottom":"0","left":"0","isLinked":""},"view_button_padding":{"unit":"px","top":"16","right":"24","bottom":"16","left":"24","isLinked":""},"floor_plan_view_button_hover_text_color":"#FFFFFF","submit_border_radius":{"unit":"px","size":"0","sizes":[]},"submit-field-border_border":"none","floor_plan_image_size_size":"large","title_typography_font_size_tablet_extra":{"unit":"px","size":"28","sizes":[]},"contents_hover_height_tablet_extra":{"unit":"px","size":"168","sizes":[]}},"elements":[],"isInner":false,"widgetType":"rhea-property-floor-plans-widget","elType":"widget"}],"isInner":"","elType":"column"}],"isInner":"","elType":"section"},{"id":"1e1a18b","settings":{"margin":{"unit":"px","top":"0","right":"0","bottom":"60","left":"0","isLinked":""},"_element_id":"rh-locations","content_width":{"unit":"px","size":"775","sizes":[]},"margin_tablet":{"unit":"px","top":"0","right":"0","bottom":"20","left":"0","isLinked":""},"margin_mobile":{"unit":"px","top":"0","right":"0","bottom":"20","left":"0","isLinked":""},"padding_tablet":{"unit":"px","top":"0","right":"10","bottom":"0","left":"10","isLinked":""},"padding":{"unit":"px","top":"120","right":"0","bottom":"0","left":"0","isLinked":""}},"elements":[{"id":"55c8a70b","settings":{"_column_size":"100"},"elements":[{"id":"45a9ec59","settings":{"title":"- Location","header_size":"span","align":"center","__globals__":{"typography_typography":"","title_color":""},"title_color":"#3A7658","typography_typography":"custom","typography_font_family":"Archivo","typography_font_size":{"unit":"px","size":"16","sizes":[]},"typography_font_weight":"600","typography_line_height":{"unit":"px","size":"25","sizes":[]},"typography_word_spacing":{"unit":"em","size":"","sizes":[]}},"elements":[],"isInner":false,"widgetType":"heading","elType":"widget"},{"id":"75ddbf7a","settings":{"title":"All Roads Lead To RealHomes","align":"center","__globals__":{"typography_typography":""},"title_color":"#0A1510","typography_typography":"custom","typography_font_family":"Archivo Black","typography_font_size":{"unit":"px","size":"64","sizes":[]},"typography_font_weight":"600","typography_line_height":{"unit":"px","size":"70","sizes":[]},"typography_font_size_tablet":{"unit":"px","size":"46","sizes":[]},"typography_font_size_mobile":{"unit":"px","size":"26","sizes":[]},"typography_line_height_tablet":{"unit":"em","size":"1.3","sizes":[]}},"elements":[],"isInner":false,"widgetType":"heading","elType":"widget"},{"id":"6c60e469","settings":{"width":{"unit":"px","size":"100","sizes":[]},"width_tablet":{"unit":"px","size":"","sizes":[]},"width_mobile":{"unit":"px","size":"","sizes":[]},"align":"center","text":"Divider","color":"#3A7658","weight":{"unit":"px","size":"3","sizes":[]},"gap":{"unit":"px","size":"0","sizes":[]},"__globals__":{"color":""}},"elements":[],"isInner":false,"widgetType":"divider","elType":"widget"}],"isInner":"","elType":"column"}],"isInner":"","elType":"section"},{"id":"342121d6","settings":{"content_width":{"unit":"px","size":"1224","sizes":[]},"margin":{"unit":"px","top":"0","right":"0","bottom":"40","left":"0","isLinked":""},"margin_tablet":{"unit":"px","top":"0","right":"0","bottom":"40","left":"0","isLinked":""},"padding_tablet":{"unit":"px","top":"0","right":"10","bottom":"0","left":"10","isLinked":""},"padding_tablet_extra":{"unit":"px","top":"0","right":"10","bottom":"0","left":"10","isLinked":""},"padding_laptop":{"unit":"px","top":"0","right":"10","bottom":"0","left":"10","isLinked":""}},"elements":[{"id":"16c2899e","settings":{"_column_size":"100"},"elements":[{"id":"62048260","settings":{"lat":"40.7128","lng":"-74.0060","height":{"unit":"px","size":"600","sizes":[]},"location_label":"RealHomes Apartments","address":"1130, Avenue Villa New York, USA","show_field_icon":"yes","container_width":{"unit":"px","size":"1400","sizes":[]},"swap_column_position":"yes","map_marker":{"url":"https:\/\/ultra.inspirylabs.com\/condominium\/wp-content\/uploads\/sites\/8\/2023\/05\/map-pin-2.svg","id":"855","size":"","alt":"","source":"library"},"show_as_infowindow":"yes","map_border_radius":{"unit":"px","size":"0","sizes":[]},"heading_typography_typography":"custom","heading_typography_font_family":"Archivo","heading_typography_font_size":{"unit":"px","size":"20","sizes":[]},"heading_typography_font_weight":"600","heading_typography_line_height":{"unit":"px","size":"28","sizes":[]},"address_typography_typography":"custom","address_typography_font_family":"Archivo","address_typography_font_size":{"unit":"px","size":"14","sizes":[]},"address_typography_font_weight":"400","address_typography_line_height":{"unit":"px","size":"26","sizes":[]},"map_custom_style":"","heading_color":"#3A7658","heading_margin_bottom":{"unit":"px","size":"0","sizes":[]}},"elements":[],"isInner":false,"widgetType":"rhea-single-property-map-widget","elType":"widget"}],"isInner":"","elType":"column"}],"isInner":"","elType":"section"},{"id":"22e64fa1","settings":{"margin_mobile":{"unit":"px","top":"0","right":"0","bottom":"0","left":"0","isLinked":""}},"elements":[{"id":"35d65c5","settings":{"_column_size":"100"},"elements":[{"id":"2e4c1161","settings":{"title":"Nearby Locations","align":"center","typography_typography":"custom","typography_font_family":"Archivo Black","typography_font_size":{"unit":"px","size":"22","sizes":[]},"typography_font_weight":"400","typography_line_height":{"unit":"px","size":"70","sizes":[]},"__globals__":{"typography_typography":""},"typography_line_height_mobile":{"unit":"em","size":"1.2","sizes":[]},"title_color":"#0A1510"},"elements":[],"isInner":false,"widgetType":"heading","elType":"widget"}],"isInner":"","elType":"column"}],"isInner":"","elType":"section"},{"id":"110c0c10","settings":{"content_width":{"unit":"px","size":"1224","sizes":[]},"structure":"40","margin":{"unit":"px","top":"14","right":"0","bottom":"0","left":"0","isLinked":""},"text_align_mobile":"center"},"elements":[{"id":"719dbe5c","settings":{"_column_size":"25","_inline_size_tablet":"50","content_position":"center"},"elements":[{"id":"e8e4679","settings":{"structure":"20"},"elements":[{"id":"420a48c7","settings":{"_column_size":"50","_inline_size":"29.283","content_position":"center"},"elements":[{"id":"19c2c347","settings":{"selected_icon":{"value":"fas fa-plane-departure","library":"fa-solid"},"view":"stacked","size":{"unit":"px","size":"24","sizes":[]},"icon_padding":{"unit":"px","size":"18","sizes":[]},"__globals__":{"primary_color":"","hover_primary_color":""},"secondary_color":"#FFFFFF","primary_color":"#3A7658","hover_primary_color":"#0A1510"},"elements":[],"isInner":false,"widgetType":"icon","elType":"widget"}],"isInner":"1","elType":"column"},{"id":"23b9b2f8","settings":{"_column_size":"50","_inline_size":"70.717","content_position":"center","space_between_widgets":"5","margin":{"unit":"px","top":"5","right":"0","bottom":"0","left":"0","isLinked":""}},"elements":[{"id":"4fbf80a0","settings":{"title":"Airport","header_size":"h5","title_color":"#0A1510","typography_typography":"custom","typography_font_family":"Archivo","typography_font_size":{"unit":"px","size":"18","sizes":[]},"typography_font_weight":"600","typography_line_height":{"unit":"px","size":"10","sizes":[]},"__globals__":{"typography_typography":""}},"elements":[],"isInner":false,"widgetType":"heading","elType":"widget"},{"id":"1e58ce2b","settings":{"title":"12.5 KM","header_size":"span","title_color":"#0A1510A6","typography_typography":"custom","typography_font_family":"Archivo","typography_font_size":{"unit":"px","size":"16","sizes":[]},"typography_font_weight":"400","_element_width":"initial","_element_custom_width":{"unit":"%","size":"100"}},"elements":[],"isInner":false,"widgetType":"heading","elType":"widget"}],"isInner":"1","elType":"column"}],"isInner":"1","elType":"section"}],"isInner":"","elType":"column"},{"id":"58583ae4","settings":{"_column_size":"25","_inline_size_tablet":"50"},"elements":[{"id":"62c1a82c","settings":{"structure":"20"},"elements":[{"id":"c5f18bd","settings":{"_column_size":"50","_inline_size":"29.283"},"elements":[{"id":"41bc252f","settings":{"selected_icon":{"value":"fas fa-bus","library":"fa-solid"},"view":"stacked","size":{"unit":"px","size":"24","sizes":[]},"icon_padding":{"unit":"px","size":"18","sizes":[]},"__globals__":{"primary_color":"","hover_primary_color":""},"secondary_color":"#FFFFFF","primary_color":"#3A7658","hover_primary_color":"#0A1510"},"elements":[],"isInner":false,"widgetType":"icon","elType":"widget"}],"isInner":"1","elType":"column"},{"id":"5a50ed58","settings":{"_column_size":"50","_inline_size":"70.717","content_position":"center","space_between_widgets":"5","margin":{"unit":"px","top":"5","right":"0","bottom":"0","left":"0","isLinked":""}},"elements":[{"id":"dc07fb3","settings":{"title":"Bus Stand","header_size":"h5","title_color":"#0A1510","typography_typography":"custom","typography_font_family":"Archivo","typography_font_size":{"unit":"px","size":"18","sizes":[]},"typography_font_weight":"600","typography_line_height":{"unit":"px","size":"10","sizes":[]},"__globals__":{"typography_typography":""}},"elements":[],"isInner":false,"widgetType":"heading","elType":"widget"},{"id":"19ef8e04","settings":{"title":"6.8 KM","header_size":"span","title_color":"#0A1510A6","typography_typography":"custom","typography_font_family":"Archivo","typography_font_size":{"unit":"px","size":"16","sizes":[]},"typography_font_weight":"400"},"elements":[],"isInner":false,"widgetType":"heading","elType":"widget"}],"isInner":"1","elType":"column"}],"isInner":"1","elType":"section"}],"isInner":"","elType":"column"},{"id":"7c740ff4","settings":{"_column_size":"25","_inline_size_tablet":"50"},"elements":[{"id":"284540dc","settings":{"structure":"20"},"elements":[{"id":"6d39c49c","settings":{"_column_size":"50","_inline_size":"29.983"},"elements":[{"id":"7db8f66c","settings":{"selected_icon":{"value":"fas fa-school","library":"fa-solid"},"view":"stacked","size":{"unit":"px","size":"24","sizes":[]},"icon_padding":{"unit":"px","size":"18","sizes":[]},"__globals__":{"primary_color":"","hover_primary_color":""},"secondary_color":"#FFFFFF","primary_color":"#3A7658","hover_primary_color":"#0A1510"},"elements":[],"isInner":false,"widgetType":"icon","elType":"widget"}],"isInner":"1","elType":"column"},{"id":"47c5018c","settings":{"_column_size":"50","_inline_size":"70.017","content_position":"center","space_between_widgets":"5","margin":{"unit":"px","top":"5","right":"0","bottom":"0","left":"0","isLinked":""}},"elements":[{"id":"61b4da1b","settings":{"title":"School","header_size":"h5","title_color":"#0A1510","typography_typography":"custom","typography_font_family":"Archivo","typography_font_size":{"unit":"px","size":"18","sizes":[]},"typography_font_weight":"600","typography_line_height":{"unit":"px","size":"10","sizes":[]},"__globals__":{"typography_typography":""}},"elements":[],"isInner":false,"widgetType":"heading","elType":"widget"},{"id":"4301334a","settings":{"title":"2.4 KM","header_size":"span","title_color":"#0A1510A6","typography_typography":"custom","typography_font_family":"Archivo","typography_font_size":{"unit":"px","size":"16","sizes":[]},"typography_font_weight":"400"},"elements":[],"isInner":false,"widgetType":"heading","elType":"widget"}],"isInner":"1","elType":"column"}],"isInner":"1","elType":"section"}],"isInner":"","elType":"column"},{"id":"6ff3f3d0","settings":{"_column_size":"25","_inline_size_tablet":"50"},"elements":[{"id":"34defa78","settings":{"structure":"20"},"elements":[{"id":"5ecb39f1","settings":{"_column_size":"50","_inline_size":"29.983"},"elements":[{"id":"75302b87","settings":{"selected_icon":{"value":"fas fa-university","library":"fa-solid"},"view":"stacked","size":{"unit":"px","size":"24","sizes":[]},"icon_padding":{"unit":"px","size":"18","sizes":[]},"__globals__":{"primary_color":"","hover_primary_color":""},"secondary_color":"#FFFFFF","primary_color":"#3A7658","hover_primary_color":"#0A1510"},"elements":[],"isInner":false,"widgetType":"icon","elType":"widget"}],"isInner":"1","elType":"column"},{"id":"528d95f","settings":{"_column_size":"50","_inline_size":"70.017","content_position":"center","space_between_widgets":"5","margin":{"unit":"px","top":"5","right":"0","bottom":"0","left":"0","isLinked":""}},"elements":[{"id":"4f9828d","settings":{"title":"Bank","header_size":"h5","title_color":"#0A1510","typography_typography":"custom","typography_font_family":"Archivo","typography_font_size":{"unit":"px","size":"18","sizes":[]},"typography_font_weight":"600","typography_line_height":{"unit":"px","size":"10","sizes":[]},"__globals__":{"typography_typography":""}},"elements":[],"isInner":false,"widgetType":"heading","elType":"widget"},{"id":"11611d65","settings":{"title":"1.8 KM","header_size":"span","title_color":"#0A1510A6","typography_typography":"custom","typography_font_family":"Archivo","typography_font_size":{"unit":"px","size":"16","sizes":[]},"typography_font_weight":"400"},"elements":[],"isInner":false,"widgetType":"heading","elType":"widget"}],"isInner":"1","elType":"column"}],"isInner":"1","elType":"section"}],"isInner":"","elType":"column"}],"isInner":"","elType":"section"},{"id":"660911fe","settings":{"content_width":{"unit":"px","size":"1224","sizes":[]},"structure":"40","margin":{"unit":"px","top":"0","right":"0","bottom":"110","left":"0","isLinked":""},"text_align_mobile":"center","margin_tablet":{"unit":"px","top":"0","right":"0","bottom":"40","left":"0","isLinked":""}},"elements":[{"id":"1aec165","settings":{"_column_size":"25","_inline_size_tablet":"50"},"elements":[{"id":"42d2b17d","settings":{"structure":"20"},"elements":[{"id":"29e47bc8","settings":{"_column_size":"50","_inline_size":"29.283"},"elements":[{"id":"2ba13083","settings":{"selected_icon":{"value":"fas fa-book","library":"fa-solid"},"view":"stacked","size":{"unit":"px","size":"24","sizes":[]},"icon_padding":{"unit":"px","size":"18","sizes":[]},"__globals__":{"primary_color":"","hover_primary_color":""},"secondary_color":"#FFFFFF","primary_color":"#3A7658","hover_primary_color":"#0A1510"},"elements":[],"isInner":false,"widgetType":"icon","elType":"widget"}],"isInner":"1","elType":"column"},{"id":"a6e83c5","settings":{"_column_size":"50","_inline_size":"70.717","content_position":"center","space_between_widgets":"5","margin":{"unit":"px","top":"5","right":"0","bottom":"0","left":"0","isLinked":""}},"elements":[{"id":"788d1684","settings":{"title":"Liabrary","header_size":"h5","title_color":"#0A1510","typography_typography":"custom","typography_font_family":"Archivo","typography_font_size":{"unit":"px","size":"18","sizes":[]},"typography_font_weight":"600","typography_line_height":{"unit":"px","size":"10","sizes":[]},"__globals__":{"typography_typography":""}},"elements":[],"isInner":false,"widgetType":"heading","elType":"widget"},{"id":"2a6d3004","settings":{"title":"0.5 KM","header_size":"span","title_color":"#0A1510A6","typography_typography":"custom","typography_font_family":"Archivo","typography_font_size":{"unit":"px","size":"16","sizes":[]},"typography_font_weight":"400","_element_width":"initial","_element_custom_width":{"unit":"%","size":"100"}},"elements":[],"isInner":false,"widgetType":"heading","elType":"widget"}],"isInner":"1","elType":"column"}],"isInner":"1","elType":"section"}],"isInner":"","elType":"column"},{"id":"24c9586b","settings":{"_column_size":"25","_inline_size_tablet":"50"},"elements":[{"id":"35808f2e","settings":{"structure":"20"},"elements":[{"id":"4bb35da3","settings":{"_column_size":"50","_inline_size":"29.283"},"elements":[{"id":"1ee91afe","settings":{"selected_icon":{"value":"fas fa-hospital-symbol","library":"fa-solid"},"view":"stacked","size":{"unit":"px","size":"24","sizes":[]},"icon_padding":{"unit":"px","size":"18","sizes":[]},"__globals__":{"primary_color":"","hover_primary_color":""},"secondary_color":"#FFFFFF","primary_color":"#3A7658","hover_primary_color":"#0A1510"},"elements":[],"isInner":false,"widgetType":"icon","elType":"widget"}],"isInner":"1","elType":"column"},{"id":"1c5537c1","settings":{"_column_size":"50","_inline_size":"70.717","content_position":"center","space_between_widgets":"5","margin":{"unit":"px","top":"5","right":"0","bottom":"0","left":"0","isLinked":""}},"elements":[{"id":"60cc04de","settings":{"title":"Hospital","header_size":"h5","title_color":"#0A1510","typography_typography":"custom","typography_font_family":"Archivo","typography_font_size":{"unit":"px","size":"18","sizes":[]},"typography_font_weight":"600","typography_line_height":{"unit":"px","size":"10","sizes":[]},"__globals__":{"typography_typography":""}},"elements":[],"isInner":false,"widgetType":"heading","elType":"widget"},{"id":"7b363ad","settings":{"title":"1.1 KM","header_size":"span","title_color":"#0A1510A6","typography_typography":"custom","typography_font_family":"Archivo","typography_font_size":{"unit":"px","size":"16","sizes":[]},"typography_font_weight":"400"},"elements":[],"isInner":false,"widgetType":"heading","elType":"widget"}],"isInner":"1","elType":"column"}],"isInner":"1","elType":"section"}],"isInner":"","elType":"column"},{"id":"336fcd8e","settings":{"_column_size":"25","_inline_size_tablet":"50"},"elements":[{"id":"3f28447d","settings":{"structure":"20"},"elements":[{"id":"7db0788","settings":{"_column_size":"50","_inline_size":"29.983"},"elements":[{"id":"4df440b3","settings":{"selected_icon":{"value":"fas fa-film","library":"fa-solid"},"view":"stacked","size":{"unit":"px","size":"24","sizes":[]},"icon_padding":{"unit":"px","size":"18","sizes":[]},"__globals__":{"primary_color":"","hover_primary_color":""},"secondary_color":"#FFFFFF","primary_color":"#3A7658","hover_primary_color":"#0A1510"},"elements":[],"isInner":false,"widgetType":"icon","elType":"widget"}],"isInner":"1","elType":"column"},{"id":"f2933e9","settings":{"_column_size":"50","_inline_size":"70.017","content_position":"center","space_between_widgets":"5","margin":{"unit":"px","top":"5","right":"0","bottom":"0","left":"0","isLinked":""}},"elements":[{"id":"662a2ed4","settings":{"title":"Cinema","header_size":"h5","title_color":"#0A1510","typography_typography":"custom","typography_font_family":"Archivo","typography_font_size":{"unit":"px","size":"18","sizes":[]},"typography_font_weight":"600","typography_line_height":{"unit":"px","size":"10","sizes":[]},"__globals__":{"typography_typography":""}},"elements":[],"isInner":false,"widgetType":"heading","elType":"widget"},{"id":"749ce6f5","settings":{"title":"2.5 KM","header_size":"span","title_color":"#0A1510A6","typography_typography":"custom","typography_font_family":"Archivo","typography_font_size":{"unit":"px","size":"16","sizes":[]},"typography_font_weight":"400"},"elements":[],"isInner":false,"widgetType":"heading","elType":"widget"}],"isInner":"1","elType":"column"}],"isInner":"1","elType":"section"}],"isInner":"","elType":"column"},{"id":"3a74358f","settings":{"_column_size":"25","_inline_size_tablet":"50"},"elements":[{"id":"2a5a0abd","settings":{"structure":"20"},"elements":[{"id":"56558edb","settings":{"_column_size":"50","_inline_size":"29.983"},"elements":[{"id":"1809de8a","settings":{"selected_icon":{"value":"fas fa-train","library":"fa-solid"},"view":"stacked","size":{"unit":"px","size":"24","sizes":[]},"icon_padding":{"unit":"px","size":"18","sizes":[]},"__globals__":{"primary_color":"","hover_primary_color":""},"secondary_color":"#FFFFFF","primary_color":"#3A7658","hover_primary_color":"#0A1510"},"elements":[],"isInner":false,"widgetType":"icon","elType":"widget"}],"isInner":"1","elType":"column"},{"id":"3a7c8b1","settings":{"_column_size":"50","_inline_size":"70.017","content_position":"center","space_between_widgets":"5","margin":{"unit":"px","top":"5","right":"0","bottom":"0","left":"0","isLinked":""}},"elements":[{"id":"49bafc6f","settings":{"title":"Metro Station\n","header_size":"h5","title_color":"#0A1510","typography_typography":"custom","typography_font_family":"Archivo","typography_font_size":{"unit":"px","size":"18","sizes":[]},"typography_font_weight":"600","typography_line_height":{"unit":"px","size":"10","sizes":[]},"__globals__":{"typography_typography":""}},"elements":[],"isInner":false,"widgetType":"heading","elType":"widget"},{"id":"5ba277c3","settings":{"title":"1.8 KM","header_size":"span","title_color":"#0A1510A6","typography_typography":"custom","typography_font_family":"Archivo","typography_font_size":{"unit":"px","size":"16","sizes":[]},"typography_font_weight":"400"},"elements":[],"isInner":false,"widgetType":"heading","elType":"widget"}],"isInner":"1","elType":"column"}],"isInner":"1","elType":"section"}],"isInner":"","elType":"column"}],"isInner":"","elType":"section"},{"id":"4a14628e","settings":{"layout":"full_width","gap":"no","custom_height":{"unit":"px","size":"398","sizes":[]},"_element_id":"rh-schedule"},"elements":[{"id":"69d241a2","settings":{"_column_size":"100","_inline_size":"100"},"elements":[{"id":"131caa90","settings":{"layout":"full_width","structure":"20","height_inner":"min-height","custom_height_inner":{"unit":"px","size":"750","sizes":[]},"padding":{"unit":"px","top":"0","right":"0","bottom":"0","left":"0","isLinked":""},"custom_height_inner_tablet":{"unit":"px","size":"0","sizes":[]},"custom_height_inner_mobile":{"unit":"px","size":"0","sizes":[]}},"elements":[{"id":"72214a8f","settings":{"_column_size":"50","_inline_size":"50","align":"flex-end","background_background":"classic","__globals__":{"background_hover_color":"","background_color":""},"padding":{"unit":"px","top":"70","right":"0","bottom":"0","left":"0","isLinked":""},"background_color":"#0A1510","_inline_size_tablet":"100","padding_tablet":{"unit":"px","top":"40","right":"20","bottom":"20","left":"20","isLinked":""},"padding_tablet_extra":{"unit":"px","top":"20","right":"0","bottom":"0","left":"20","isLinked":""},"padding_laptop":{"unit":"px","top":"0","right":"0","bottom":"0","left":"20","isLinked":""}},"elements":[{"id":"285c7453","settings":{"title":"- Location","header_size":"span","title_color":"#FFFFFF00","_margin":{"unit":"px","top":"0","right":"0","bottom":"10","left":"0","isLinked":""},"_element_width":"initial","_element_custom_width":{"unit":"em","size":"37","sizes":[]},"_element_custom_width_tablet":{"unit":"em","size":"","sizes":[]},"_element_custom_width_mobile":{"unit":"em","size":"","sizes":[]},"__globals__":{"typography_typography":"globals\/typography?id=c44fa1e"},"_z_index":"-1"},"elements":[],"isInner":false,"widgetType":"heading","elType":"widget"},{"id":"4a03408a","settings":{"title":"- Quick Connect","header_size":"span","title_color":"#FFFFFF","_margin":{"unit":"px","top":"0","right":"0","bottom":"10","left":"0","isLinked":""},"_element_width":"initial","_element_custom_width":{"unit":"em","size":"37","sizes":[]},"_element_custom_width_tablet":{"unit":"em","size":"100","sizes":[]},"_element_custom_width_mobile":{"unit":"em","size":"","sizes":[]},"__globals__":{"typography_typography":"globals\/typography?id=c44fa1e","title_color":""},"align_tablet":"center","typography_typography":"custom","typography_font_family":"Archivo","typography_font_size":{"unit":"px","size":"16","sizes":[]},"typography_font_weight":"600","typography_line_height":{"unit":"px","size":"25","sizes":[]},"typography_word_spacing":{"unit":"em","size":"","sizes":[]}},"elements":[],"isInner":false,"widgetType":"heading","elType":"widget"},{"id":"2fb61504","settings":{"title":"Get in touch with us for any questions &amp; help","typography_typography":"custom","typography_font_family":"Archivo Black","typography_font_size":{"unit":"px","size":"40","sizes":[]},"typography_font_weight":"400","title_color":"#FFFFFF","_element_width":"initial","_element_custom_width":{"unit":"em","size":"37.5","sizes":[]},"_element_custom_width_tablet":{"unit":"rem","size":"100","sizes":[]},"_element_custom_width_mobile":{"unit":"rem","size":"","sizes":[]},"__globals__":{"typography_typography":""},"typography_line_height":{"unit":"em","size":"1.1","sizes":[]},"_padding":{"unit":"px","top":"0","right":"20","bottom":"4","left":"0","isLinked":""},"align_tablet":"center","typography_font_size_tablet":{"unit":"px","size":"40","sizes":[]},"typography_font_size_mobile":{"unit":"px","size":"26","sizes":[]},"_padding_tablet":{"unit":"px","top":"0","right":"0","bottom":"20","left":"0","isLinked":""},"_padding_mobile":{"unit":"px","top":"0","right":"0","bottom":"20","left":"0","isLinked":""}},"elements":[],"isInner":false,"widgetType":"heading","elType":"widget"},{"id":"37a5f728","settings":{"width":{"unit":"px","size":"0","sizes":[]},"width_tablet":{"unit":"px","size":"","sizes":[]},"width_mobile":{"unit":"px","size":"","sizes":[]},"align":"left","align_tablet":"center","text":"Divider","color":"#FFFFFF","_element_width":"initial","_element_custom_width":{"unit":"%","size":"100","sizes":[]},"_element_custom_width_tablet":{"unit":"%","size":"100","sizes":[]},"_element_custom_width_mobile":{"unit":"%","size":"","sizes":[]},"__globals__":{"color":""},"gap":{"unit":"px","size":"0","sizes":[]},"_element_custom_width_laptop":{"unit":"%","size":"","sizes":[]},"_element_custom_width_tablet_extra":{"unit":"%","size":"","sizes":[]},"_element_vertical_align":"flex-end"},"elements":[],"isInner":false,"widgetType":"divider","elType":"widget"},{"id":"2fd82b71","settings":{"width":{"unit":"px","size":"60","sizes":[]},"width_tablet":{"unit":"px","size":"","sizes":[]},"width_mobile":{"unit":"px","size":"","sizes":[]},"align":"left","align_tablet":"center","text":"Divider","color":"#FFFFFF","weight":{"unit":"px","size":"3","sizes":[]},"_element_width":"initial","_element_custom_width":{"unit":"px","size":"598","sizes":[]},"_element_custom_width_tablet":{"unit":"%","size":"100","sizes":[]},"_element_custom_width_mobile":{"unit":"%","size":"","sizes":[]},"__globals__":{"color":""},"_element_vertical_align":"flex-end"},"elements":[],"isInner":false,"widgetType":"divider","elType":"widget"}],"isInner":"1","elType":"column"},{"id":"3dbe75ef","settings":{"_column_size":"50","_inline_size":"50","background_background":"classic","background_image":{"url":"https:\/\/ultra.inspirylabs.com\/condominium\/wp-content\/uploads\/sites\/8\/2023\/04\/kitchen.jpg","id":"1098","size":"","alt":"","source":"library"},"background_position":"center center","background_repeat":"no-repeat","background_size":"cover","hide_tablet":"hidden-tablet","hide_mobile":"hidden-mobile"},"elements":[],"isInner":"1","elType":"column"}],"isInner":"1","elType":"section"},{"id":"14084540","settings":{"content_width":{"unit":"px","size":"1200","sizes":[]},"margin":{"unit":"px","top":"-452","right":"0","bottom":"0","left":"0","isLinked":""},"padding":{"unit":"px","top":"0","right":"0","bottom":"0","left":"0","isLinked":""},"margin_tablet":{"unit":"px","top":"0","right":"0","bottom":"0","left":"0","isLinked":""},"margin_mobile":{"unit":"px","top":"0","right":"0","bottom":"0","left":"0","isLinked":""}},"elements":[{"id":"516ec21a","settings":{"_column_size":"100","background_background":"classic","background_color":"#FFFFFF","box_shadow_box_shadow_type":"yes","box_shadow_box_shadow":{"horizontal":"0","vertical":"16","blur":"80","spread":"0","color":"rgba(0, 0, 0, 0.118)"},"padding":{"unit":"px","top":"60","right":"60","bottom":"40","left":"60","isLinked":""},"padding_tablet":{"unit":"px","top":"40","right":"20","bottom":"40","left":"20","isLinked":""}},"elements":[{"id":"170eea","settings":{"title":"Schedule a tour","typography_typography":"custom","typography_font_family":"Archivo Black","typography_font_size":{"unit":"px","size":"32","sizes":[]},"typography_font_weight":"600","typography_line_height":{"unit":"px","size":"70","sizes":[]},"__globals__":{"typography_typography":""},"typography_font_size_mobile":{"unit":"px","size":"26","sizes":[]},"typography_line_height_mobile":{"unit":"em","size":"1.2","sizes":[]},"title_color":"#0A1510"},"elements":[],"isInner":false,"widgetType":"heading","elType":"widget"},{"id":"722f9692","settings":{"rhea_add_field_select":[{"_id":"94e0293","rhea_select_field_type":"name","rhea_field_label":"Full name","rhea_field_placeholder":"Full name","rhea_required_field":"yes","rhea_field_size":"50%","rhea_field_size_mobile":"100%","rhea_error_message":"*Name field is required"},{"_id":"6d33441","rhea_select_field_type":"number","rhea_field_label":"Phone number","rhea_field_placeholder":"Phone number","rhea_field_size":"50%","rhea_field_size_mobile":"100%"},{"_id":"1ecf4bc","rhea_select_field_type":"email","rhea_field_label":"Email","rhea_field_placeholder":"Email address","rhea_required_field":"yes","rhea_error_message":"*Please enter valid email address"},{"_id":"ceb1797","rhea_select_field_type":"message","rhea_field_label":"Message","rhea_field_placeholder":"Message"}],"rhea_submit_text":"Schedule a Tour","submit_button_inline":"yes","submit_button_custom_size":{"unit":"px","size":"228","sizes":[]},"field-height":{"unit":"px","size":"60","sizes":[]},"textarea-height":{"unit":"px","size":"140","sizes":[]},"field-between-space":{"unit":"px","size":"12","sizes":[]},"rhea-submit-button-size":{"unit":"px","size":"252","sizes":[]},"rhea_submit_align":"right","field-placeholder-color":"#0A151033","field-background":"#E6EDED","submit-button-text-hover-color":"#FFFFFF","submit-field-border_border":"none","submit-field-border-hover_border":"none","__globals__":{"field-placeholder-color":"","submit-button-bg-color":"","submit-button-bg-hover-color":"","submit-field-border_color":"globals\/colors?id=secondary","submit-field-border-hover_color":"","submit-button-animate-hover-color":""},"submit-button-bg-color":"#3A7658","submit-button-bg-hover-color":"#0A1510","submit-field-border_color":"#54595F","submit-field-border-hover_color":"#0A1510","rhea_submit_align_mobile":"center","submit-button-animate-hover-color":"#0A1510","button_type":"slide-in-left","label_typography_typography":"custom","label_typography_font_family":"Archivo","label_typography_font_size":{"unit":"px","size":"22","sizes":[]},"label_typography_font_weight":"300","label_typography_line_height":{"unit":"px","size":"35","sizes":[]},"fields_typography_typography":"custom","fields_typography_font_family":"Archivo","fields_typography_font_size":{"unit":"px","size":"22","sizes":[]},"fields_typography_font_weight":"300","fields_typography_line_height":{"unit":"px","size":"35","sizes":[]},"checkbox_radio_typography_typography":"custom","checkbox_radio_typography_font_family":"Archivo","checkbox_radio_typography_font_size":{"unit":"px","size":"22","sizes":[]},"checkbox_radio_typography_font_weight":"300","checkbox_radio_typography_line_height":{"unit":"px","size":"35","sizes":[]},"submit_typography_typography":"custom","submit_typography_font_family":"Archivo","submit_typography_font_size":{"unit":"px","size":"20","sizes":[]},"submit_typography_font_weight":"600","submit_typography_line_height":{"unit":"px","size":"35","sizes":[]},"gdpr_required_typography_typography":"custom","gdpr_required_typography_font_family":"Archivo","gdpr_required_typography_font_size":{"unit":"px","size":"22","sizes":[]},"gdpr_required_typography_font_weight":"300","gdpr_required_typography_line_height":{"unit":"px","size":"35","sizes":[]},"gdpr_text_typography_typography":"custom","gdpr_text_typography_font_family":"Archivo","gdpr_text_typography_font_size":{"unit":"px","size":"22","sizes":[]},"gdpr_text_typography_font_weight":"300","gdpr_text_typography_line_height":{"unit":"px","size":"35","sizes":[]},"submit_message_text_typography_typography":"custom","submit_message_text_typography_font_family":"Archivo","submit_message_text_typography_font_size":{"unit":"px","size":"22","sizes":[]},"submit_message_text_typography_font_weight":"300","submit_message_text_typography_line_height":{"unit":"px","size":"35","sizes":[]},"error_message_text_typography_typography":"custom","error_message_text_typography_font_family":"Archivo","error_message_text_typography_font_size":{"unit":"px","size":"14","sizes":[]},"error_message_text_typography_font_weight":"300","error_message_text_typography_line_height":{"unit":"px","size":"35","sizes":[]},"submit-button-padding":{"unit":"px","top":"15","right":"10","bottom":"15","left":"10","isLinked":""}},"elements":[],"isInner":false,"widgetType":"rhea-inquiry-form","elType":"widget"}],"isInner":"1","elType":"column"}],"isInner":"1","elType":"section"}],"isInner":"","elType":"column"}],"isInner":"","elType":"section"},{"id":"1ea82bcf","settings":{"content_width":{"unit":"px","size":"1240","sizes":[]},"content_position":"middle","structure":"40","margin":{"unit":"px","top":"40","right":"0","bottom":"0","left":"0","isLinked":""},"text_align_mobile":"center","padding_tablet":{"unit":"px","top":"0","right":"20","bottom":"0","left":"20","isLinked":""}},"elements":[{"id":"185c1020","settings":{"_column_size":"25","_inline_size_tablet":"50"},"elements":[{"id":"76e11285","settings":{"structure":"20"},"elements":[{"id":"c2f95bf","settings":{"_column_size":"50","_inline_size":"31.132","content_position":"center"},"elements":[{"id":"5e589b54","settings":{"image":{"url":"https:\/\/ultra.inspirylabs.com\/condominium\/wp-content\/uploads\/sites\/8\/2023\/04\/image_360.png","id":"41","size":"","alt":"","source":"library"}},"elements":[],"isInner":false,"widgetType":"image","elType":"widget"}],"isInner":"1","elType":"column"},{"id":"78b39dbf","settings":{"_column_size":"50","_inline_size":"68.868","content_position":"center"},"elements":[{"id":"1ce08a1c","settings":{"title":"Jenny Wilson","typography_typography":"custom","typography_font_family":"Archivo","typography_font_size":{"unit":"px","size":"18","sizes":[]},"typography_font_weight":"600","typography_line_height":{"unit":"px","size":"25","sizes":[]},"typography_word_spacing":{"unit":"em","size":"","sizes":[]},"_element_width":"initial","_element_custom_width":{"unit":"%","size":"98.222"},"__globals__":{"typography_typography":""},"title_color":"#0A1510"},"elements":[],"isInner":false,"widgetType":"heading","elType":"widget"},{"id":"17e53e8f","settings":{"title":"Real Estate Agent","title_color":"#0A151099","typography_typography":"custom","typography_font_family":"Archivo","typography_font_size":{"unit":"px","size":"16","sizes":[]},"typography_font_weight":"400","typography_line_height":{"unit":"px","size":"25","sizes":[]},"typography_word_spacing":{"unit":"em","size":"","sizes":[]},"__globals__":{"typography_typography":""}},"elements":[],"isInner":false,"widgetType":"heading","elType":"widget"}],"isInner":"1","elType":"column"}],"isInner":"1","elType":"section"}],"isInner":"","elType":"column"},{"id":"2e033f29","settings":{"_column_size":"25","_inline_size":"21.333","space_between_widgets":"0","_inline_size_tablet":"50"},"elements":[{"id":"7141be86","settings":{"title":"contact@realhomes.io","typography_typography":"custom","typography_font_family":"Archivo","typography_font_size":{"unit":"px","size":"18","sizes":[]},"typography_font_weight":"400","typography_line_height":{"unit":"em","size":"1.6","sizes":[]},"__globals__":{"typography_typography":""},"title_color":"#0A1510"},"elements":[],"isInner":false,"widgetType":"heading","elType":"widget"},{"id":"71dfaf6e","settings":{"title":"(222) 546 7594","typography_typography":"custom","typography_font_family":"Archivo","typography_font_size":{"unit":"px","size":"18","sizes":[]},"typography_font_weight":"400","typography_line_height":{"unit":"em","size":"1.6","sizes":[]},"__globals__":{"typography_typography":""},"title_color":"#0A1510"},"elements":[],"isInner":false,"widgetType":"heading","elType":"widget"}],"isInner":"","elType":"column"},{"id":"4057596e","settings":{"_column_size":"25","_inline_size":"19.766","space_between_widgets":"0","_inline_size_tablet":"50"},"elements":[{"id":"5c2cc077","settings":{"title":"1130, Avenue Villa\nNewyork, USA","typography_typography":"custom","typography_font_family":"Archivo","typography_font_size":{"unit":"px","size":"18","sizes":[]},"typography_font_weight":"400","typography_line_height":{"unit":"em","size":"1.6","sizes":[]},"__globals__":{"typography_typography":""},"title_color":"#0A1510"},"elements":[],"isInner":false,"widgetType":"heading","elType":"widget"}],"isInner":"","elType":"column"},{"id":"4401abc4","settings":{"_column_size":"25","_inline_size":"33.901","space_between_widgets":"0","_inline_size_tablet":"50"},"elements":[{"id":"1bb08139","settings":{"title":"Would you like to visit the property?","typography_typography":"custom","typography_font_family":"Archivo","typography_font_size":{"unit":"px","size":"18","sizes":[]},"typography_font_weight":"400","typography_line_height":{"unit":"em","size":"1.6","sizes":[]},"_element_width":"initial","_element_custom_width":{"unit":"%","size":"103.131"},"__globals__":{"typography_typography":""},"title_color":"#0A1510"},"elements":[],"isInner":false,"widgetType":"heading","elType":"widget"},{"id":"5a6df64e","settings":{"text":"Schedule a Tour","align":"left","typography_typography":"custom","typography_font_family":"Archivo","typography_font_size":{"unit":"px","size":"18","sizes":[]},"typography_font_weight":"600","typography_text_decoration":"underline","typography_line_height":{"unit":"px","size":"28","sizes":[]},"background_color":"#61CE7000","text_padding":{"unit":"px","top":"0","right":"0","bottom":"0","left":"0","isLinked":"1"},"__globals__":{"button_text_color":"","hover_color":""},"button_text_color":"#3A7658","hover_color":"#0A1510","align_mobile":"center","link":{"url":"#rh-schedule","is_external":"","nofollow":"","custom_attributes":""}},"elements":[],"isInner":false,"widgetType":"button","elType":"widget"}],"isInner":"","elType":"column"}],"isInner":"","elType":"section"},{"id":"5336be69","settings":[],"elements":[{"id":"351aa1fa","settings":{"_column_size":"100"},"elements":[{"id":"6d5da5ef","settings":{"space":{"unit":"px","size":"10","sizes":[]}},"elements":[],"isInner":false,"widgetType":"spacer","elType":"widget"}],"isInner":"","elType":"column"}],"isInner":"","elType":"section"}],"page_settings":[],"version":"0.4","title":"Condominium Homepage","type":"page"}